sphinxserve/__main__.py
sphinxserve/lib.py
sphinxserve/__init__.py
sphinxserve-0.7.4.data/scripts/sphinxserve
sphinxserve-0.7.4.dist-info/top_level.txt
sphinxserve-0.7.4.dist-info/METADATA
sphinxserve-0.7.4.dist-info/DESCRIPTION.rst
sphinxserve-0.7.4.dist-info/metadata.json
sphinxserve-0.7.4.dist-info/WHEEL
sphinxserve-0.7.4.dist-info/RECORD
