Metadata-Version: 2.0
Name: sphinxserve
Version: 0.7.4
Summary: sphinxserve renders sphinx docs monitoring file changes
Home-page: https://github.com/mzdaniel/sphinxserve
Author: Daniel Mizyrycki
Author-email: mzdaniel@glidelink.net
License: MIT License
Keywords: sphinx
Requires-Dist: flask-sockets (>=0.1)
Requires-Dist: gevent (>=1.1b2)
Requires-Dist: loadconfig (>=0.1)
Requires-Dist: sphinx (>=1.2.3)
Requires-Dist: watchdog (>=0.8.3)
